notebook_checker/__init__.py
notebook_checker/templates/__init__.py
notebook_checker/templates/clear_log.py
notebook_checker/templates/global_check.py
notebook_checker/templates/load_logger.py
notebook_checker/templates/log_error.py
notebook_checker-0.0.5.dist-info/LICENSE
notebook_checker-0.0.5.dist-info/METADATA
notebook_checker-0.0.5.dist-info/WHEEL
notebook_checker-0.0.5.dist-info/top_level.txt
notebook_checker-0.0.5.dist-info/RECORD
