Metadata-Version: 2.1
Name: notebook-checker
Version: 0.0.5
Summary: A package to check notebook files for the use of globals inside functions
Home-page: https://github.com/uvaai/notebook_checks
Author: TF Doolan
Author-email: t.f.doolan@uva.nl
Classifier: Programming Language :: Python :: 3
Classifier: License :: OSI Approved :: MIT License
Classifier: Operating System :: OS Independent
Requires-Python: >=3.6
License-File: LICENSE
